Workbook

Sheet Read Me
A1: Test Case Execution Workbook – Fashion E-commerce Application
A2: Document ID | B2: QT-FEC-TCS-001 v1.0 (companion to Test Case Specification PDF; parent plan QT-FEC-STP-001)
A3: Standard | B3: ISO/IEC/IEEE 29119-3:2021 – Test Case Specification, Test Procedure Specification, Test Execution Log
A4: Application | B4: https://fashion-ecommerce-we-lunb.bolt.host
A5: Prepared by | B5: Ram – Senior Test Manager, Quality Thought
A7: Sheets
A8: Test Cases | B8: 290 functional test cases (positive + negative per acceptance criterion)
A9: E2E Procedures | B9: 24 end-to-end journeys, one row per step (107 steps)
A10: E2E Summary | B10: One row per E2E procedure; status derived automatically from its steps
A11: Traceability | B11: User story → test cases → E2E procedures, with live execution counts
A12: Dashboard | B12: Live execution status by module, priority and type (formulas – no manual edits)
A14: How to execute
A15: Yellow cells | B15: Are the only cells testers edit: Actual Result, Status, Defect ID, Executed By, Execution Date, Browser / Device, Build ID, Comments
A16: Status values | B16: Not Run (default), Pass, Fail, Blocked, Deferred – pick from the drop-down
A17: On failure | B17: Log a defect against the User Story ID (e.g. US-19), then enter the defect ID in the row
A18: Critical cases | B18: Execute on every browser/device in test plan §13.2; add a row per extra run or record them in Comments
A19: Example row | B19: Test Cases row 2 (TC-US01-01) shows a filled example of the execution columns – reset it to Not Run before the first real cycle
A20: Assumed values | B20: Lockout threshold, session timeout, return window, coupon and gift card values are example test data pending Product Owner confirmation

Sheet Dashboard
A1: Execution Dashboard
A2: All values are formulas over the Test Cases and E2E sheets – they update as Status is changed.
A4: Functional test cases by module | B4: Total | C4: Pass | D4: Fail | E4: Blocked | F4: Not Run | G4: Deferred | H4: Pass %
A5: M01 – Account Registration & Authentication | B5: =COUNTIF('Test Cases'!$B$2:$B$291,"M01") -> 40 | C5: =COUNTIFS('Test Cases'!$B$2:$B$291,"M01",'Test Cases'!$O$2:$O$291,"Pass") -> 1 | D5: =COUNTIFS('Test Cases'!$B$2:$B$291,"M01",'Test Cases'!$O$2:$O$291,"Fail") -> 0 | E5: =COUNTIFS('Test Cases'!$B$2:$B$291,"M01",'Test Cases'!$O$2:$O$291,"Blocked") -> 0 | F5: =COUNTIFS('Test Cases'!$B$2:$B$291,"M01",'Test Cases'!$O$2:$O$291,"Not Run") -> 39 | G5: =COUNTIFS('Test Cases'!$B$2:$B$291,"M01",'Test Cases'!$O$2:$O$291,"Deferred") -> 0 | H5: =IF(B5=0,0,C5/B5) -> 0.025
A6: M02 – Home Page, Navigation & Content | B6: =COUNTIF('Test Cases'!$B$2:$B$291,"M02") -> 20 | C6: =COUNTIFS('Test Cases'!$B$2:$B$291,"M02",'Test Cases'!$O$2:$O$291,"Pass") -> 0 | D6: =COUNTIFS('Test Cases'!$B$2:$B$291,"M02",'Test Cases'!$O$2:$O$291,"Fail") -> 0 | E6: =COUNTIFS('Test Cases'!$B$2:$B$291,"M02",'Test Cases'!$O$2:$O$291,"Blocked") -> 0 | F6: =COUNTIFS('Test Cases'!$B$2:$B$291,"M02",'Test Cases'!$O$2:$O$291,"Not Run") -> 20 | G6: =COUNTIFS('Test Cases'!$B$2:$B$291,"M02",'Test Cases'!$O$2:$O$291,"Deferred") -> 0 | H6: =IF(B6=0,0,C6/B6) -> 0
A7: M03 – Product Discovery: Search, Browse & Filters | B7: =COUNTIF('Test Cases'!$B$2:$B$291,"M03") -> 32 | C7: =COUNTIFS('Test Cases'!$B$2:$B$291,"M03",'Test Cases'!$O$2:$O$291,"Pass") -> 0 | D7: =COUNTIFS('Test Cases'!$B$2:$B$291,"M03",'Test Cases'!$O$2:$O$291,"Fail") -> 0 | E7: =COUNTIFS('Test Cases'!$B$2:$B$291,"M03",'Test Cases'!$O$2:$O$291,"Blocked") -> 0 | F7: =COUNTIFS('Test Cases'!$B$2:$B$291,"M03",'Test Cases'!$O$2:$O$291,"Not Run") -> 32 | G7: =COUNTIFS('Test Cases'!$B$2:$B$291,"M03",'Test Cases'!$O$2:$O$291,"Deferred") -> 0 | H7: =IF(B7=0,0,C7/B7) -> 0
A8: M04 – Product Detail Page (PDP) | B8: =COUNTIF('Test Cases'!$B$2:$B$291,"M04") -> 34 | C8: =COUNTIFS('Test Cases'!$B$2:$B$291,"M04",'Test Cases'!$O$2:$O$291,"Pass") -> 0 | D8: =COUNTIFS('Test Cases'!$B$2:$B$291,"M04",'Test Cases'!$O$2:$O$291,"Fail") -> 0 | E8: =COUNTIFS('Test Cases'!$B$2:$B$291,"M04",'Test Cases'!$O$2:$O$291,"Blocked") -> 0 | F8: =COUNTIFS('Test Cases'!$B$2:$B$291,"M04",'Test Cases'!$O$2:$O$291,"Not Run") -> 34 | G8: =COUNTIFS('Test Cases'!$B$2:$B$291,"M04",'Test Cases'!$O$2:$O$291,"Deferred") -> 0 | H8: =IF(B8=0,0,C8/B8) -> 0
A9: M05 – Shopping Cart | B9: =COUNTIF('Test Cases'!$B$2:$B$291,"M05") -> 32 | C9: =COUNTIFS('Test Cases'!$B$2:$B$291,"M05",'Test Cases'!$O$2:$O$291,"Pass") -> 0 | D9: =COUNTIFS('Test Cases'!$B$2:$B$291,"M05",'Test Cases'!$O$2:$O$291,"Fail") -> 0 | E9: =COUNTIFS('Test Cases'!$B$2:$B$291,"M05",'Test Cases'!$O$2:$O$291,"Blocked") -> 0 | F9: =COUNTIFS('Test Cases'!$B$2:$B$291,"M05",'Test Cases'!$O$2:$O$291,"Not Run") -> 32 | G9: =COUNTIFS('Test Cases'!$B$2:$B$291,"M05",'Test Cases'!$O$2:$O$291,"Deferred") -> 0 | H9: =IF(B9=0,0,C9/B9) -> 0
A10: M06 – Checkout & Payments | B10: =COUNTIF('Test Cases'!$B$2:$B$291,"M06") -> 38 | C10: =COUNTIFS('Test Cases'!$B$2:$B$291,"M06",'Test Cases'!$O$2:$O$291,"Pass") -> 0 | D10: =COUNTIFS('Test Cases'!$B$2:$B$291,"M06",'Test Cases'!$O$2:$O$291,"Fail") -> 0 | E10: =COUNTIFS('Test Cases'!$B$2:$B$291,"M06",'Test Cases'!$O$2:$O$291,"Blocked") -> 0 | F10: =COUNTIFS('Test Cases'!$B$2:$B$291,"M06",'Test Cases'!$O$2:$O$291,"Not Run") -> 38 | G10: =COUNTIFS('Test Cases'!$B$2:$B$291,"M06",'Test Cases'!$O$2:$O$291,"Deferred") -> 0 | H10: =IF(B10=0,0,C10/B10) -> 0
A11: M07 – Orders, Tracking, Returns & Cancellations | B11: =COUNTIF('Test Cases'!$B$2:$B$291,"M07") -> 26 | C11: =COUNTIFS('Test Cases'!$B$2:$B$291,"M07",'Test Cases'!$O$2:$O$291,"Pass") -> 0 | D11: =COUNTIFS('Test Cases'!$B$2:$B$291,"M07",'Test Cases'!$O$2:$O$291,"Fail") -> 0 | E11: =COUNTIFS('Test Cases'!$B$2:$B$291,"M07",'Test Cases'!$O$2:$O$291,"Blocked") -> 0 | F11: =COUNTIFS('Test Cases'!$B$2:$B$291,"M07",'Test Cases'!$O$2:$O$291,"Not Run") -> 26 | G11: =COUNTIFS('Test Cases'!$B$2:$B$291,"M07",'Test Cases'!$O$2:$O$291,"Deferred") -> 0 | H11: =IF(B11=0,0,C11/B11) -> 0
A12: M08 – Account Management | B12: =COUNTIF('Test Cases'!$B$2:$B$291,"M08") -> 20 | C12: =COUNTIFS('Test Cases'!$B$2:$B$291,"M08",'Test Cases'!$O$2:$O$291,"Pass") -> 0 | D12: =COUNTIFS('Test Cases'!$B$2:$B$291,"M08",'Test Cases'!$O$2:$O$291,"Fail") -> 0 | E12: =COUNTIFS('Test Cases'!$B$2:$B$291,"M08",'Test Cases'!$O$2:$O$291,"Blocked") -> 0 | F12: =COUNTIFS('Test Cases'!$B$2:$B$291,"M08",'Test Cases'!$O$2:$O$291,"Not Run") -> 20 | G12: =COUNTIFS('Test Cases'!$B$2:$B$291,"M08",'Test Cases'!$O$2:$O$291,"Deferred") -> 0 | H12: =IF(B12=0,0,C12/B12) -> 0
A13: M09 – Notifications, Promotions & Content | B13: =COUNTIF('Test Cases'!$B$2:$B$291,"M09") -> 16 | C13: =COUNTIFS('Test Cases'!$B$2:$B$291,"M09",'Test Cases'!$O$2:$O$291,"Pass") -> 0 | D13: =COUNTIFS('Test Cases'!$B$2:$B$291,"M09",'Test Cases'!$O$2:$O$291,"Fail") -> 0 | E13: =COUNTIFS('Test Cases'!$B$2:$B$291,"M09",'Test Cases'!$O$2:$O$291,"Blocked") -> 0 | F13: =COUNTIFS('Test Cases'!$B$2:$B$291,"M09",'Test Cases'!$O$2:$O$291,"Not Run") -> 16 | G13: =COUNTIFS('Test Cases'!$B$2:$B$291,"M09",'Test Cases'!$O$2:$O$291,"Deferred") -> 0 | H13: =IF(B13=0,0,C13/B13) -> 0
A14: M10 – Cross-Cutting: Performance, Security, Compatibility & Accessibility | B14: =COUNTIF('Test Cases'!$B$2:$B$291,"M10") -> 32 | C14: =COUNTIFS('Test Cases'!$B$2:$B$291,"M10",'Test Cases'!$O$2:$O$291,"Pass") -> 0 | D14: =COUNTIFS('Test Cases'!$B$2:$B$291,"M10",'Test Cases'!$O$2:$O$291,"Fail") -> 0 | E14: =COUNTIFS('Test Cases'!$B$2:$B$291,"M10",'Test Cases'!$O$2:$O$291,"Blocked") -> 0 | F14: =COUNTIFS('Test Cases'!$B$2:$B$291,"M10",'Test Cases'!$O$2:$O$291,"Not Run") -> 32 | G14: =COUNTIFS('Test Cases'!$B$2:$B$291,"M10",'Test Cases'!$O$2:$O$291,"Deferred") -> 0 | H14: =IF(B14=0,0,C14/B14) -> 0
A15: Total | B15: =SUM(B5:B14) -> 290 | C15: =SUM(C5:C14) -> 1 | D15: =SUM(D5:D14) -> 0 | E15: =SUM(E5:E14) -> 0 | F15: =SUM(F5:F14) -> 289 | G15: =SUM(G5:G14) -> 0 | H15: =IF(B15=0,0,C15/B15) -> 0.0034482759
A17: By priority | B17: Total | C17: Pass | D17: Fail | E17: Blocked | F17: Not Run | G17: Deferred | H17: Pass %
A18: Critical | B18: =COUNTIF('Test Cases'!$E$2:$E$291,"Critical") -> 62 | C18: =COUNTIFS('Test Cases'!$E$2:$E$291,"Critical",'Test Cases'!$O$2:$O$291,"Pass") -> 0 | D18: =COUNTIFS('Test Cases'!$E$2:$E$291,"Critical",'Test Cases'!$O$2:$O$291,"Fail") -> 0 | E18: =COUNTIFS('Test Cases'!$E$2:$E$291,"Critical",'Test Cases'!$O$2:$O$291,"Blocked") -> 0 | F18: =COUNTIFS('Test Cases'!$E$2:$E$291,"Critical",'Test Cases'!$O$2:$O$291,"Not Run") -> 62 | G18: =COUNTIFS('Test Cases'!$E$2:$E$291,"Critical",'Test Cases'!$O$2:$O$291,"Deferred") -> 0 | H18: =IF(B18=0,0,C18/B18) -> 0
A19: High | B19: =COUNTIF('Test Cases'!$E$2:$E$291,"High") -> 76 | C19: =COUNTIFS('Test Cases'!$E$2:$E$291,"High",'Test Cases'!$O$2:$O$291,"Pass") -> 1 | D19: =COUNTIFS('Test Cases'!$E$2:$E$291,"High",'Test Cases'!$O$2:$O$291,"Fail") -> 0 | E19: =COUNTIFS('Test Cases'!$E$2:$E$291,"High",'Test Cases'!$O$2:$O$291,"Blocked") -> 0 | F19: =COUNTIFS('Test Cases'!$E$2:$E$291,"High",'Test Cases'!$O$2:$O$291,"Not Run") -> 75 | G19: =COUNTIFS('Test Cases'!$E$2:$E$291,"High",'Test Cases'!$O$2:$O$291,"Deferred") -> 0 | H19: =IF(B19=0,0,C19/B19) -> 0.013157895
A20: Medium | B20: =COUNTIF('Test Cases'!$E$2:$E$291,"Medium") -> 112 | C20: =COUNTIFS('Test Cases'!$E$2:$E$291,"Medium",'Test Cases'!$O$2:$O$291,"Pass") -> 0 | D20: =COUNTIFS('Test Cases'!$E$2:$E$291,"Medium",'Test Cases'!$O$2:$O$291,"Fail") -> 0 | E20: =COUNTIFS('Test Cases'!$E$2:$E$291,"Medium",'Test Cases'!$O$2:$O$291,"Blocked") -> 0 | F20: =COUNTIFS('Test Cases'!$E$2:$E$291,"Medium",'Test Cases'!$O$2:$O$291,"Not Run") -> 112 | G20: =COUNTIFS('Test Cases'!$E$2:$E$291,"Medium",'Test Cases'!$O$2:$O$291,"Deferred") -> 0 | H20: =IF(B20=0,0,C20/B20) -> 0
A21: Low | B21: =COUNTIF('Test Cases'!$E$2:$E$291,"Low") -> 40 | C21: =COUNTIFS('Test Cases'!$E$2:$E$291,"Low",'Test Cases'!$O$2:$O$291,"Pass") -> 0 | D21: =COUNTIFS('Test Cases'!$E$2:$E$291,"Low",'Test Cases'!$O$2:$O$291,"Fail") -> 0 | E21: =COUNTIFS('Test Cases'!$E$2:$E$291,"Low",'Test Cases'!$O$2:$O$291,"Blocked") -> 0 | F21: =COUNTIFS('Test Cases'!$E$2:$E$291,"Low",'Test Cases'!$O$2:$O$291,"Not Run") -> 40 | G21: =COUNTIFS('Test Cases'!$E$2:$E$291,"Low",'Test Cases'!$O$2:$O$291,"Deferred") -> 0 | H21: =IF(B21=0,0,C21/B21) -> 0
A23: By type | B23: Total | C23: Pass | D23: Fail | E23: Blocked | F23: Not Run | G23: Deferred | H23: Pass %
A24: Positive | B24: =COUNTIF('Test Cases'!$H$2:$H$291,"Positive") -> 145 | C24: =COUNTIFS('Test Cases'!$H$2:$H$291,"Positive",'Test Cases'!$O$2:$O$291,"Pass") -> 1 | D24: =COUNTIFS('Test Cases'!$H$2:$H$291,"Positive",'Test Cases'!$O$2:$O$291,"Fail") -> 0 | E24: =COUNTIFS('Test Cases'!$H$2:$H$291,"Positive",'Test Cases'!$O$2:$O$291,"Blocked") -> 0 | F24: =COUNTIFS('Test Cases'!$H$2:$H$291,"Positive",'Test Cases'!$O$2:$O$291,"Not Run") -> 144 | G24: =COUNTIFS('Test Cases'!$H$2:$H$291,"Positive",'Test Cases'!$O$2:$O$291,"Deferred") -> 0 | H24: =IF(B24=0,0,C24/B24) -> 0.0068965517
A25: Negative | B25: =COUNTIF('Test Cases'!$H$2:$H$291,"Negative") -> 145 | C25: =COUNTIFS('Test Cases'!$H$2:$H$291,"Negative",'Test Cases'!$O$2:$O$291,"Pass") -> 0 | D25: =COUNTIFS('Test Cases'!$H$2:$H$291,"Negative",'Test Cases'!$O$2:$O$291,"Fail") -> 0 | E25: =COUNTIFS('Test Cases'!$H$2:$H$291,"Negative",'Test Cases'!$O$2:$O$291,"Blocked") -> 0 | F25: =COUNTIFS('Test Cases'!$H$2:$H$291,"Negative",'Test Cases'!$O$2:$O$291,"Not Run") -> 145 | G25: =COUNTIFS('Test Cases'!$H$2:$H$291,"Negative",'Test Cases'!$O$2:$O$291,"Deferred") -> 0 | H25: =IF(B25=0,0,C25/B25) -> 0
A27: End-to-end procedures | B27: Total | C27: Pass | D27: Fail | E27: Blocked | F27: Not Run | G27: In Progress | H27: Pass %
A28: E2E procedures | B28: =COUNTA('E2E Summary'!$A$2:$A$25) -> 24 | C28: =COUNTIF('E2E Summary'!$J$2:$J$25,"Pass") -> 0 | D28: =COUNTIF('E2E Summary'!$J$2:$J$25,"Fail") -> 0 | E28: =COUNTIF('E2E Summary'!$J$2:$J$25,"Blocked") -> 0 | F28: =COUNTIF('E2E Summary'!$J$2:$J$25,"Not Run") -> 24 | G28: =COUNTIF('E2E Summary'!$J$2:$J$25,"In Progress") -> 0 | H28: =IF(B28=0,0,C28/B28) -> 0
A30: User stories fully passed (of 60) | B30: =COUNTIF(Traceability!$M$2:$M$61,"Pass") -> 0
A31: Open failures linked to Critical stories | B31: =COUNTIFS('Test Cases'!$E$2:$E$291,"Critical",'Test Cases'!$O$2:$O$291,"Fail") -> 0

Sheet Test Cases
A1: TC ID | B1: Module | C1: User Story | D1: Story Title | E1: Priority | F1: AC # | G1: Acceptance Criterion | H1: Type | I1: Title / Objective | J1: Preconditions | K1: Test Steps | L1: Test Data | M1: Expected Result | N1: Actual Result | O1: Status | P1: Defect ID | Q1: Executed By | R1: Execution Date | S1: Browser / Device | T1: Build ID | U1: Comments
A2: TC-US01-01 | B2: M01 | C2: US-01 | D2: Register account with email & password | E2: High | F2: 1 | G2: Registration form validates required fields (name, email, password, confirm password) | H2: Positive | I2: Register with all mandatory fields valid | J2: User is logged out; Registration page is reachable from header "Sign up / Register"; test mailbox available | K2: 1. Open Register page 2. Enter full name, unique email, valid password and matching confirm password 3. Click Register | L2: Name: Asha Rao; Email: qa.reg01+<ts>@testmail.com; Password: Qa@12345 | M2: Account is created; success message or redirect shown; no field-level errors | N2: Account created; success toast shown; redirected to homepage logged in | O2: Pass | Q2: Ram | R2: =DATE(2026,10,8) -> 46303 | S2: Chrome 129 / Win 11
A3: TC-US01-02 | B3: M01 | C3: US-01 | D3: Register account with email & password | E3: High | F3: 1 | G3: Registration form validates required fields (name, email, password, confirm password) | H3: Negative | I3: Submit with each mandatory field blank / invalid email format | J3: User is logged out; Registration page is reachable from header "Sign up / Register"; test mailbox available | K3: 1. Leave Name blank and submit 2. Repeat for Email, Password, Confirm Password 3. Enter email "asha@", "asha.com", "@test.com" and submit | L3: Blank values; malformed emails | M3: Form is not submitted; inline error shown against the specific field; entered valid data is retained | O3: Not Run
A4: TC-US01-03 | B4: M01 | C4: US-01 | D4: Register account with email & password | E4: High | F4: 2 | G4: Password enforces minimum strength rules (length, character mix) | H4: Positive | I4: Accept password meeting strength policy | J4: User is logged out; Registration page is reachable from header "Sign up / Register"; test mailbox available | K4: 1. Enter password with min length, upper, lower, digit and special character 2. Submit with other fields valid | L4: Password: Qa@12345 (8 chars) and Str0ng!Pass2026 | M4: Password accepted; strength indicator (if any) shows Strong; account created | O4: Not Run
A5: TC-US01-04 | B5: M01 | C5: US-01 | D5: Register account with email & password | E5: High | F5: 2 | G5: Password enforces minimum strength rules (length, character mix) | H5: Negative | I5: Reject weak passwords at boundary | J5: User is logged out; Registration page is reachable from header "Sign up / Register"; test mailbox available | K5: 1. Enter password one character below min length 2. Enter all-lowercase, all-digit and no-special-character passwords 3. Enter password and non-matching confirm | L5: Qa@1234 (7 chars); password; 12345678; Qa123456; Confirm: Qa@12346 | M5: Each attempt is rejected with a message stating the unmet rule; mismatch error shown for confirm field | O5: Not Run
A6: TC-US01-05 | B6: M01 | C6: US-01 | D6: Register account with email & password | E6: High | F6: 3 | G6: Duplicate email registration is blocked with a clear error message | H6: Positive | I6: Register with a never-used email succeeds | J6: User is logged out; Registration page is reachable from header "Sign up / Register"; test mailbox available | K6: 1. Register with an email not in the system | L6: qa.unique+<ts>@testmail.com | M6: Registration succeeds; one account exists for this email | O6: Not Run
A7: TC-US01-06 | B7: M01 | C7: US-01 | D7: Register account with email & password | E7: High | F7: 3 | G7: Duplicate email registration is blocked with a clear error message | H7: Negative | I7: Register again with an existing email (case variants) | J7: User is logged out; Registration page is reachable from header "Sign up / Register"; test mailbox available | K7: 1. Register with an already registered email 2. Repeat with the same email in UPPERCASE and with leading/trailing spaces | L7: existing: qa.reg01@testmail.com; QA.REG01@TESTMAIL.COM; " qa.reg01@testmail.com " | M7: Registration blocked with clear "email already registered" message and a link to login/reset; no second account created | O7: Not Run
A8: TC-US01-07 | B8: M01 | C8: US-01 | D8: Register account with email & password | E8: High | F8: 4 | G8: Successful registration logs the user in or redirects to login/confirmation | H8: Positive | I8: Post-registration landing is correct | J8: User is logged out; Registration page is reachable from header "Sign up / Register"; test mailbox available | K8: 1. Complete a valid registration 2. Observe landing page and header | L8: Valid new user | M8: User is logged in (name shown in header) or redirected to login/confirmation page as per design; welcome/verification email received if applicable | O8: Not Run
A9: TC-US01-08 | B9: M01 | C9: US-01 | D9: Register account with email & password | E9: High | F9: 4 | G9: Successful registration logs the user in or redirects to login/confirmation | H9: Negative | I9: Refresh / back after registration does not re-submit | J9: User is logged out; Registration page is reachable from header "Sign up / Register"; test mailbox available | K9: 1. After successful registration press browser Back 2. Press F5 on the confirmation page | L9: — | M9: No duplicate account or error; user is not asked to resubmit form data | O9: Not Run
A10: TC-US02-01 | B10: M01 | C10: US-02 | D10: Login with email & password | E10: Critical | F10: 1 | G10: Valid credentials log the user in and redirect to homepage/account | H10: Positive | I10: Login with valid credentials | J10: Registered, active account exists; user is logged out | K10: 1. Open Login 2. Enter registered email and correct password 3. Click Login | L10: qa.user01@testmail.com / Qa@12345 | M10: User logged in; redirected to homepage or My Account; user name visible in header | O10: Not Run
A11: TC-US02-02 | B11: M01 | C11: US-02 | D11: Login with email & password | E11: Critical | F11: 1 | G11: Valid credentials log the user in and redirect to homepage/account | H11: Negative | I11: Login with email in different case / extra spaces | J11: Registered, active account exists; user is logged out | K11: 1. Enter email in uppercase with trailing space and correct password 2. Submit | L11: " QA.USER01@TESTMAIL.COM " | M11: Login succeeds (email treated case-insensitively and trimmed) or a clear validation message is shown — never a system error | O11: Not Run
A12: TC-US02-03 | B12: M01 | C12: US-02 | D12: Login with email & password | E12: Critical | F12: 2 | G12: Invalid credentials show a generic, non-revealing error message | H12: Positive | I12: Error message is generic for wrong password | J12: Registered, active account exists; user is logged out | K12: 1. Enter registered email with wrong password 2. Submit | L12: qa.user01@testmail.com / Wrong@123 | M12: Generic message such as "Invalid email or password"; password field cleared; no indication which field is wrong | O12: Not Run
A13: TC-US02-04 | B13: M01 | C13: US-02 | D13: Login with email & password | E13: Critical | F13: 2 | G13: Invalid credentials show a generic, non-revealing error message | H13: Negative | I13: Error message is identical for unregistered email | J13: Registered, active account exists; user is logged out | K13: 1. Enter unregistered email with any password 2. Compare message with previous case | L13: nobody+<ts>@testmail.com | M13: Same generic message and same response time pattern; system does not reveal whether the email exists | O13: Not Run
A14: TC-US02-05 | B14: M01 | C14: US-02 | D14: Login with email & password | E14: Critical | F14: 3 | G14: Account locks or throttles after repeated failed attempts | H14: Positive | I14: Login still allowed below lockout threshold | J14: Registered, active account exists; user is logged out | K14: 1. Enter wrong password (threshold-1) times 2. Enter correct password | L14: Threshold per policy (e.g. 5) | M14: Login succeeds; failed-attempt counter resets | O14: Not Run
... A291: TC-US60-04 | B291: M10 | C291: US-60 | D291: Error pages (404 / 500) | E291: Low | F291: 2 | G291: Server errors are caught and shown as a friendly message, not a raw stack trace | H291: Negative | I291: No technical details leaked | J291: Test environment available; user on the relevant page | K291: 1. Inspect 500 response body and headers | L291: — | M291: No stack trace, framework version or internal paths revealed | O291: Not Run

Sheet E2E Procedures
A1: E2E ID | B1: Journey | C1: Priority | D1: Stories Covered | E1: Preconditions | F1: Test Data | G1: Step | H1: Action | I1: Expected Result | J1: Actual Result | K1: Status | L1: Defect ID | M1: Executed By | N1: Execution Date | O1: Browser / Device | P1: Comments
A2: E2E-01 | B2: New customer: register, discover, buy with card and receive confirmation | C2: Critical | D2: US-01, 02, 12, 14, 15, 17, 18, 19, 22, 25, 29, 30, 31, 32, 33, 34, 35, 36, 50 | E2: Logged out; product P-1001 (Red/L in stock, price 1,499); coupon SAVE10 active; card sandbox | F2: New email qa.e2e01+<ts>@testmail.com; Password Qa@12345; Card 4111 1111 1111 1111, 12/30, 123; PIN 500081 | G2: 1 | H2: Open the homepage and click Register | I2: Registration form displayed with all mandatory fields | K2: Not Run
A3: E2E-01 | B3: New customer: register, discover, buy with card and receive confirmation | C3: Critical | D3: US-01, 02, 12, 14, 15, 17, 18, 19, 22, 25, 29, 30, 31, 32, 33, 34, 35, 36, 50 | E3: Logged out; product P-1001 (Red/L in stock, price 1,499); coupon SAVE10 active; card sandbox | F3: New email qa.e2e01+<ts>@testmail.com; Password Qa@12345; Card 4111 1111 1111 1111, 12/30, 123; PIN 500081 | G3: 2 | H3: Register with valid details | I3: Account created; user logged in (name in header) or redirected to login | K3: Not Run
A4: E2E-01 | B4: New customer: register, discover, buy with card and receive confirmation | C4: Critical | D4: US-01, 02, 12, 14, 15, 17, 18, 19, 22, 25, 29, 30, 31, 32, 33, 34, 35, 36, 50 | E4: Logged out; product P-1001 (Red/L in stock, price 1,499); coupon SAVE10 active; card sandbox | F4: New email qa.e2e01+<ts>@testmail.com; Password Qa@12345; Card 4111 1111 1111 1111, 12/30, 123; PIN 500081 | G4: 3 | H4: Search for "maxi dress" | I4: Relevant results listed; P-1001 present | K4: Not Run
A5: E2E-01 | B5: New customer: register, discover, buy with card and receive confirmation | C5: Critical | D5: US-01, 02, 12, 14, 15, 17, 18, 19, 22, 25, 29, 30, 31, 32, 33, 34, 35, 36, 50 | E5: Logged out; product P-1001 (Red/L in stock, price 1,499); coupon SAVE10 active; card sandbox | F5: New email qa.e2e01+<ts>@testmail.com; Password Qa@12345; Card 4111 1111 1111 1111, 12/30, 123; PIN 500081 | G5: 4 | H5: Apply filter Size L and Colour Red; sort Price Low-High; toggle List view | I5: Only Red/L products shown in ascending price; filter chips visible; layout switches without losing filters | K5: Not Run
A6: E2E-01 | B6: New customer: register, discover, buy with card and receive confirmation | C6: Critical | D6: US-01, 02, 12, 14, 15, 17, 18, 19, 22, 25, 29, 30, 31, 32, 33, 34, 35, 36, 50 | E6: Logged out; product P-1001 (Red/L in stock, price 1,499); coupon SAVE10 active; card sandbox | F6: New email qa.e2e01+<ts>@testmail.com; Password Qa@12345; Card 4111 1111 1111 1111, 12/30, 123; PIN 500081 | G6: 5 | H6: Open P-1001; verify details, size chart and recommended products | I6: Title, price, images, fabric and size chart correct; recommendations link to valid PDPs | K6: Not Run
A7: E2E-01 | B7: New customer: register, discover, buy with card and receive confirmation | C7: Critical | D7: US-01, 02, 12, 14, 15, 17, 18, 19, 22, 25, 29, 30, 31, 32, 33, 34, 35, 36, 50 | E7: Logged out; product P-1001 (Red/L in stock, price 1,499); coupon SAVE10 active; card sandbox | F7: New email qa.e2e01+<ts>@testmail.com; Password Qa@12345; Card 4111 1111 1111 1111, 12/30, 123; PIN 500081 | G7: 6 | H7: Select Red / L and click Add to Cart (qty 2) | I7: Header cart count = 2; mini-cart shows Red/L × 2 | K7: Not Run
A8: E2E-01 | B8: New customer: register, discover, buy with card and receive confirmation | C8: Critical | D8: US-01, 02, 12, 14, 15, 17, 18, 19, 22, 25, 29, 30, 31, 32, 33, 34, 35, 36, 50 | E8: Logged out; product P-1001 (Red/L in stock, price 1,499); coupon SAVE10 active; card sandbox | F8: New email qa.e2e01+<ts>@testmail.com; Password Qa@12345; Card 4111 1111 1111 1111, 12/30, 123; PIN 500081 | G8: 7 | H8: Open cart; check delivery estimate for PIN 500081; apply coupon SAVE10 | I8: Delivery cost/date shown; subtotal 2,998; discount 299.80; tax/shipping per rule; total matches oracle | K8: Not Run
A9: E2E-01 | B9: New customer: register, discover, buy with card and receive confirmation | C9: Critical | D9: US-01, 02, 12, 14, 15, 17, 18, 19, 22, 25, 29, 30, 31, 32, 33, 34, 35, 36, 50 | E9: Logged out; product P-1001 (Red/L in stock, price 1,499); coupon SAVE10 active; card sandbox | F9: New email qa.e2e01+<ts>@testmail.com; Password Qa@12345; Card 4111 1111 1111 1111, 12/30, 123; PIN 500081 | G9: 8 | H9: Proceed to checkout; add shipping address | I9: Address validated and selected | K9: Not Run
A10: E2E-01 | B10: New customer: register, discover, buy with card and receive confirmation | C10: Critical | D10: US-01, 02, 12, 14, 15, 17, 18, 19, 22, 25, 29, 30, 31, 32, 33, 34, 35, 36, 50 | E10: Logged out; product P-1001 (Red/L in stock, price 1,499); coupon SAVE10 active; card sandbox | F10: New email qa.e2e01+<ts>@testmail.com; Password Qa@12345; Card 4111 1111 1111 1111, 12/30, 123; PIN 500081 | G10: 9 | H10: Select Standard shipping | I10: Shipping cost and ETA shown; total recalculated | K10: Not Run
A11: E2E-01 | B11: New customer: register, discover, buy with card and receive confirmation | C11: Critical | D11: US-01, 02, 12, 14, 15, 17, 18, 19, 22, 25, 29, 30, 31, 32, 33, 34, 35, 36, 50 | E11: Logged out; product P-1001 (Red/L in stock, price 1,499); coupon SAVE10 active; card sandbox | F11: New email qa.e2e01+<ts>@testmail.com; Password Qa@12345; Card 4111 1111 1111 1111, 12/30, 123; PIN 500081 | G11: 10 | H11: Pay with test card | I11: Payment success; redirected to confirmation | K11: Not Run
A12: E2E-01 | B12: New customer: register, discover, buy with card and receive confirmation | C12: Critical | D12: US-01, 02, 12, 14, 15, 17, 18, 19, 22, 25, 29, 30, 31, 32, 33, 34, 35, 36, 50 | E12: Logged out; product P-1001 (Red/L in stock, price 1,499); coupon SAVE10 active; card sandbox | F12: New email qa.e2e01+<ts>@testmail.com; Password Qa@12345; Card 4111 1111 1111 1111, 12/30, 123; PIN 500081 | G12: 11 | H12: Verify confirmation page | I12: Order number, items, totals and address correct | K12: Not Run
A13: E2E-01 | B13: New customer: register, discover, buy with card and receive confirmation | C13: Critical | D13: US-01, 02, 12, 14, 15, 17, 18, 19, 22, 25, 29, 30, 31, 32, 33, 34, 35, 36, 50 | E13: Logged out; product P-1001 (Red/L in stock, price 1,499); coupon SAVE10 active; card sandbox | F13: New email qa.e2e01+<ts>@testmail.com; Password Qa@12345; Card 4111 1111 1111 1111, 12/30, 123; PIN 500081 | G13: 12 | H13: Check mailbox and My Orders | I13: Confirmation email received with matching details; order listed with status Placed/Confirmed | K13: Not Run
... A108: E2E-24 | B108: Sale pricing through to invoice | C108: Medium | D108: US-52, 29, 45 | E108: Sale item MRP 2,000, sale 1,500 | F108: — | G108: 3 | H108: Download invoice | I108: Invoice shows correct price, discount and tax | K108: Not Run

Sheet E2E Summary
A1: E2E ID | B1: Journey | C1: Priority | D1: Stories Covered | E1: Steps | F1: Passed | G1: Failed | H1: Blocked | I1: Not Run | J1: Procedure Status
A2: E2E-01 | B2: New customer: register, discover, buy with card and receive confirmation | C2: Critical | D2: US-01, 02, 12, 14, 15, 17, 18, 19, 22, 25, 29, 30, 31, 32, 33, 34, 35, 36, 50 | E2: =COUNTIF('E2E Procedures'!$A$2:$A$108,A2) -> 12 | F2: =COUNTIFS('E2E Procedures'!$A$2:$A$108,A2,'E2E Procedures'!$K$2:$K$108,"Pass") -> 0 | G2: =COUNTIFS('E2E Procedures'!$A$2:$A$108,A2,'E2E Procedures'!$K$2:$K$108,"Fail") -> 0 | H2: =COUNTIFS('E2E Procedures'!$A$2:$A$108,A2,'E2E Procedures'!$K$2:$K$108,"Blocked") -> 0 | I2: =COUNTIFS('E2E Procedures'!$A$2:$A$108,A2,'E2E Procedures'!$K$2:$K$108,"Not Run") -> 12 | J2: =IF(G2>0,"Fail",IF(H2>0,"Blocked",IF(F2=E2,"Pass",IF(I2=E2,"Not Run","In Progress")))) -> Not Run
A3: E2E-02 | B3: Guest checkout with UPI and order lookup, then account creation | C3: High | D3: US-07, 25, 29, 32, 34, 36, 40 | E3: =COUNTIF('E2E Procedures'!$A$2:$A$108,A3) -> 6 | F3: =COUNTIFS('E2E Procedures'!$A$2:$A$108,A3,'E2E Procedures'!$K$2:$K$108,"Pass") -> 0 | G3: =COUNTIFS('E2E Procedures'!$A$2:$A$108,A3,'E2E Procedures'!$K$2:$K$108,"Fail") -> 0 | H3: =COUNTIFS('E2E Procedures'!$A$2:$A$108,A3,'E2E Procedures'!$K$2:$K$108,"Blocked") -> 0 | I3: =COUNTIFS('E2E Procedures'!$A$2:$A$108,A3,'E2E Procedures'!$K$2:$K$108,"Not Run") -> 6 | J3: =IF(G3>0,"Fail",IF(H3>0,"Blocked",IF(F3=E3,"Pass",IF(I3=E3,"Not Run","In Progress")))) -> Not Run
A4: E2E-03 | B4: Returning customer: login, wishlist to cart, saved address and card, gift card split | C4: High | D4: US-02, 24, 28, 39, 47, 48, 49, 34, 36 | E4: =COUNTIF('E2E Procedures'!$A$2:$A$108,A4) -> 6 | F4: =COUNTIFS('E2E Procedures'!$A$2:$A$108,A4,'E2E Procedures'!$K$2:$K$108,"Pass") -> 0 | G4: =COUNTIFS('E2E Procedures'!$A$2:$A$108,A4,'E2E Procedures'!$K$2:$K$108,"Fail") -> 0 | H4: =COUNTIFS('E2E Procedures'!$A$2:$A$108,A4,'E2E Procedures'!$K$2:$K$108,"Blocked") -> 0 | I4: =COUNTIFS('E2E Procedures'!$A$2:$A$108,A4,'E2E Procedures'!$K$2:$K$108,"Not Run") -> 6 | J4: =IF(G4>0,"Fail",IF(H4>0,"Blocked",IF(F4=E4,"Pass",IF(I4=E4,"Not Run","In Progress")))) -> Not Run
A5: E2E-04 | B5: Social login purchase journey | C5: Medium | D5: US-03, 12, 25, 34, 36 | E5: =COUNTIF('E2E Procedures'!$A$2:$A$108,A5) -> 3 | F5: =COUNTIFS('E2E Procedures'!$A$2:$A$108,A5,'E2E Procedures'!$K$2:$K$108,"Pass") -> 0 | G5: =COUNTIFS('E2E Procedures'!$A$2:$A$108,A5,'E2E Procedures'!$K$2:$K$108,"Fail") -> 0 | H5: =COUNTIFS('E2E Procedures'!$A$2:$A$108,A5,'E2E Procedures'!$K$2:$K$108,"Blocked") -> 0 | I5: =COUNTIFS('E2E Procedures'!$A$2:$A$108,A5,'E2E Procedures'!$K$2:$K$108,"Not Run") -> 3 | J5: =IF(G5>0,"Fail",IF(H5>0,"Blocked",IF(F5=E5,"Pass",IF(I5=E5,"Not Run","In Progress")))) -> Not Run
A6: E2E-05 | B6: Password reset, then secure purchase | C6: High | D6: US-04, 02, 05, 06 | E6: =COUNTIF('E2E Procedures'!$A$2:$A$108,A6) -> 5 | F6: =COUNTIFS('E2E Procedures'!$A$2:$A$108,A6,'E2E Procedures'!$K$2:$K$108,"Pass") -> 0 | G6: =COUNTIFS('E2E Procedures'!$A$2:$A$108,A6,'E2E Procedures'!$K$2:$K$108,"Fail") -> 0 | H6: =COUNTIFS('E2E Procedures'!$A$2:$A$108,A6,'E2E Procedures'!$K$2:$K$108,"Blocked") -> 0 | I6: =COUNTIFS('E2E Procedures'!$A$2:$A$108,A6,'E2E Procedures'!$K$2:$K$108,"Not Run") -> 5 | J6: =IF(G6>0,"Fail",IF(H6>0,"Blocked",IF(F6=E6,"Pass",IF(I6=E6,"Not Run","In Progress")))) -> Not Run
A7: E2E-06 | B7: Payment failure then successful retry without losing cart | C7: Critical | D7: US-34, 35, 37, 29 | E7: =COUNTIF('E2E Procedures'!$A$2:$A$108,A7) -> 4 | F7: =COUNTIFS('E2E Procedures'!$A$2:$A$108,A7,'E2E Procedures'!$K$2:$K$108,"Pass") -> 0 | G7: =COUNTIFS('E2E Procedures'!$A$2:$A$108,A7,'E2E Procedures'!$K$2:$K$108,"Fail") -> 0 | H7: =COUNTIFS('E2E Procedures'!$A$2:$A$108,A7,'E2E Procedures'!$K$2:$K$108,"Blocked") -> 0 | I7: =COUNTIFS('E2E Procedures'!$A$2:$A$108,A7,'E2E Procedures'!$K$2:$K$108,"Not Run") -> 4 | J7: =IF(G7>0,"Fail",IF(H7>0,"Blocked",IF(F7=E7,"Pass",IF(I7=E7,"Not Run","In Progress")))) -> Not Run
A8: E2E-07 | B8: Duplicate-order prevention under double-click and network retry | C8: Critical | D8: US-37, 36, 59 | E8: =COUNTIF('E2E Procedures'!$A$2:$A$108,A8) -> 5 | F8: =COUNTIFS('E2E Procedures'!$A$2:$A$108,A8,'E2E Procedures'!$K$2:$K$108,"Pass") -> 0 | G8: =COUNTIFS('E2E Procedures'!$A$2:$A$108,A8,'E2E Procedures'!$K$2:$K$108,"Fail") -> 0 | H8: =COUNTIFS('E2E Procedures'!$A$2:$A$108,A8,'E2E Procedures'!$K$2:$K$108,"Blocked") -> 0 | I8: =COUNTIFS('E2E Procedures'!$A$2:$A$108,A8,'E2E Procedures'!$K$2:$K$108,"Not Run") -> 5 | J8: =IF(G8>0,"Fail",IF(H8>0,"Blocked",IF(F8=E8,"Pass",IF(I8=E8,"Not Run","In Progress")))) -> Not Run
A9: E2E-08 | B9: Last-unit race condition between two customers | C9: Critical | D9: US-20, 26, 37 | E9: =COUNTIF('E2E Procedures'!$A$2:$A$108,A9) -> 4 | F9: =COUNTIFS('E2E Procedures'!$A$2:$A$108,A9,'E2E Procedures'!$K$2:$K$108,"Pass") -> 0 | G9: =COUNTIFS('E2E Procedures'!$A$2:$A$108,A9,'E2E Procedures'!$K$2:$K$108,"Fail") -> 0 | H9: =COUNTIFS('E2E Procedures'!$A$2:$A$108,A9,'E2E Procedures'!$K$2:$K$108,"Blocked") -> 0 | I9: =COUNTIFS('E2E Procedures'!$A$2:$A$108,A9,'E2E Procedures'!$K$2:$K$108,"Not Run") -> 4 | J9: =IF(G9>0,"Fail",IF(H9>0,"Blocked",IF(F9=E9,"Pass",IF(I9=E9,"Not Run","In Progress")))) -> Not Run
A10: E2E-09 | B10: Cancel an order before shipping and receive refund | C10: High | D10: US-40, 42, 44, 50 | E10: =COUNTIF('E2E Procedures'!$A$2:$A$108,A10) -> 4 | F10: =COUNTIFS('E2E Procedures'!$A$2:$A$108,A10,'E2E Procedures'!$K$2:$K$108,"Pass") -> 0 | G10: =COUNTIFS('E2E Procedures'!$A$2:$A$108,A10,'E2E Procedures'!$K$2:$K$108,"Fail") -> 0 | H10: =COUNTIFS('E2E Procedures'!$A$2:$A$108,A10,'E2E Procedures'!$K$2:$K$108,"Blocked") -> 0 | I10: =COUNTIFS('E2E Procedures'!$A$2:$A$108,A10,'E2E Procedures'!$K$2:$K$108,"Not Run") -> 4 | J10: =IF(G10>0,"Fail",IF(H10>0,"Blocked",IF(F10=E10,"Pass",IF(I10=E10,"Not Run","In Progress")))) -> Not Run
A11: E2E-10 | B11: Ship and track an order, then return an item, track refund and download invoice | C11: High | D11: US-40, 41, 43, 44, 45, 50 | E11: =COUNTIF('E2E Procedures'!$A$2:$A$108,A11) -> 6 | F11: =COUNTIFS('E2E Procedures'!$A$2:$A$108,A11,'E2E Procedures'!$K$2:$K$108,"Pass") -> 0 | G11: =COUNTIFS('E2E Procedures'!$A$2:$A$108,A11,'E2E Procedures'!$K$2:$K$108,"Fail") -> 0 | H11: =COUNTIFS('E2E Procedures'!$A$2:$A$108,A11,'E2E Procedures'!$K$2:$K$108,"Blocked") -> 0 | I11: =COUNTIFS('E2E Procedures'!$A$2:$A$108,A11,'E2E Procedures'!$K$2:$K$108,"Not Run") -> 6 | J11: =IF(G11>0,"Fail",IF(H11>0,"Blocked",IF(F11=E11,"Pass",IF(I11=E11,"Not Run","In Progress")))) -> Not Run
A12: E2E-11 | B12: Exchange a delivered item for a different size | C12: Medium | D12: US-43, 19, 50 | E12: =COUNTIF('E2E Procedures'!$A$2:$A$108,A12) -> 3 | F12: =COUNTIFS('E2E Procedures'!$A$2:$A$108,A12,'E2E Procedures'!$K$2:$K$108,"Pass") -> 0 | G12: =COUNTIFS('E2E Procedures'!$A$2:$A$108,A12,'E2E Procedures'!$K$2:$K$108,"Fail") -> 0 | H12: =COUNTIFS('E2E Procedures'!$A$2:$A$108,A12,'E2E Procedures'!$K$2:$K$108,"Blocked") -> 0 | I12: =COUNTIFS('E2E Procedures'!$A$2:$A$108,A12,'E2E Procedures'!$K$2:$K$108,"Not Run") -> 3 | J12: =IF(G12>0,"Fail",IF(H12>0,"Blocked",IF(F12=E12,"Pass",IF(I12=E12,"Not Run","In Progress")))) -> Not Run
A13: E2E-12 | B13: Coupon rules across the purchase | C13: High | D13: US-30, 29, 26, 27 | E13: =COUNTIF('E2E Procedures'!$A$2:$A$108,A13) -> 4 | F13: =COUNTIFS('E2E Procedures'!$A$2:$A$108,A13,'E2E Procedures'!$K$2:$K$108,"Pass") -> 0 | G13: =COUNTIFS('E2E Procedures'!$A$2:$A$108,A13,'E2E Procedures'!$K$2:$K$108,"Fail") -> 0 | H13: =COUNTIFS('E2E Procedures'!$A$2:$A$108,A13,'E2E Procedures'!$K$2:$K$108,"Blocked") -> 0 | I13: =COUNTIFS('E2E Procedures'!$A$2:$A$108,A13,'E2E Procedures'!$K$2:$K$108,"Not Run") -> 4 | J13: =IF(G13>0,"Fail",IF(H13>0,"Blocked",IF(F13=E13,"Pass",IF(I13=E13,"Not Run","In Progress")))) -> Not Run
... A25: E2E-24 | B25: Sale pricing through to invoice | C25: Medium | D25: US-52, 29, 45 | E25: =COUNTIF('E2E Procedures'!$A$2:$A$108,A25) -> 3 | F25: =COUNTIFS('E2E Procedures'!$A$2:$A$108,A25,'E2E Procedures'!$K$2:$K$108,"Pass") -> 0 | G25: =COUNTIFS('E2E Procedures'!$A$2:$A$108,A25,'E2E Procedures'!$K$2:$K$108,"Fail") -> 0 | H25: =COUNTIFS('E2E Procedures'!$A$2:$A$108,A25,'E2E Procedures'!$K$2:$K$108,"Blocked") -> 0 | I25: =COUNTIFS('E2E Procedures'!$A$2:$A$108,A25,'E2E Procedures'!$K$2:$K$108,"Not Run") -> 3 | J25: =IF(G25>0,"Fail",IF(H25>0,"Blocked",IF(F25=E25,"Pass",IF(I25=E25,"Not Run","In Progress")))) -> Not Run

Sheet Traceability
A1: User Story | B1: Title | C1: Module | D1: Priority | E1: Acceptance Criteria | F1: Test Cases | G1: First TC | H1: Last TC | I1: E2E Procedures | J1: Passed | K1: Failed | L1: Not Run | M1: Story Status
A2: US-01 | B2: Register account with email & password | C2: M01 | D2: High | E2: 4 | F2: =COUNTIF('Test Cases'!$C$2:$C$291,A2) -> 8 | G2: TC-US01-01 | H2: TC-US01-08 | I2: E2E-01 | J2: =COUNTIFS('Test Cases'!$C$2:$C$291,A2,'Test Cases'!$O$2:$O$291,"Pass") -> 1 | K2: =COUNTIFS('Test Cases'!$C$2:$C$291,A2,'Test Cases'!$O$2:$O$291,"Fail") -> 0 | L2: =COUNTIFS('Test Cases'!$C$2:$C$291,A2,'Test Cases'!$O$2:$O$291,"Not Run") -> 7 | M2: =IF(K2>0,"Fail",IF(J2=F2,"Pass",IF(L2=F2,"Not Run","In Progress"))) -> In Progress
A3: US-02 | B3: Login with email & password | C3: M01 | D3: Critical | E3: 3 | F3: =COUNTIF('Test Cases'!$C$2:$C$291,A3) -> 6 | G3: TC-US02-01 | H3: TC-US02-06 | I3: E2E-01, E2E-03, E2E-05, E2E-13 | J3: =COUNTIFS('Test Cases'!$C$2:$C$291,A3,'Test Cases'!$O$2:$O$291,"Pass") -> 0 | K3: =COUNTIFS('Test Cases'!$C$2:$C$291,A3,'Test Cases'!$O$2:$O$291,"Fail") -> 0 | L3: =COUNTIFS('Test Cases'!$C$2:$C$291,A3,'Test Cases'!$O$2:$O$291,"Not Run") -> 6 | M3: =IF(K3>0,"Fail",IF(J3=F3,"Pass",IF(L3=F3,"Not Run","In Progress"))) -> Not Run
A4: US-03 | B4: Social / third-party login | C4: M01 | D4: Medium | E4: 3 | F4: =COUNTIF('Test Cases'!$C$2:$C$291,A4) -> 6 | G4: TC-US03-01 | H4: TC-US03-06 | I4: E2E-04 | J4: =COUNTIFS('Test Cases'!$C$2:$C$291,A4,'Test Cases'!$O$2:$O$291,"Pass") -> 0 | K4: =COUNTIFS('Test Cases'!$C$2:$C$291,A4,'Test Cases'!$O$2:$O$291,"Fail") -> 0 | L4: =COUNTIFS('Test Cases'!$C$2:$C$291,A4,'Test Cases'!$O$2:$O$291,"Not Run") -> 6 | M4: =IF(K4>0,"Fail",IF(J4=F4,"Pass",IF(L4=F4,"Not Run","In Progress"))) -> Not Run
A5: US-04 | B5: Forgot / reset password | C5: M01 | D5: High | E5: 3 | F5: =COUNTIF('Test Cases'!$C$2:$C$291,A5) -> 6 | G5: TC-US04-01 | H5: TC-US04-06 | I5: E2E-05 | J5: =COUNTIFS('Test Cases'!$C$2:$C$291,A5,'Test Cases'!$O$2:$O$291,"Pass") -> 0 | K5: =COUNTIFS('Test Cases'!$C$2:$C$291,A5,'Test Cases'!$O$2:$O$291,"Fail") -> 0 | L5: =COUNTIFS('Test Cases'!$C$2:$C$291,A5,'Test Cases'!$O$2:$O$291,"Not Run") -> 6 | M5: =IF(K5>0,"Fail",IF(J5=F5,"Pass",IF(L5=F5,"Not Run","In Progress"))) -> Not Run
A6: US-05 | B6: Logout | C6: M01 | D6: Medium | E6: 2 | F6: =COUNTIF('Test Cases'!$C$2:$C$291,A6) -> 4 | G6: TC-US05-01 | H6: TC-US05-04 | I6: E2E-05, E2E-17 | J6: =COUNTIFS('Test Cases'!$C$2:$C$291,A6,'Test Cases'!$O$2:$O$291,"Pass") -> 0 | K6: =COUNTIFS('Test Cases'!$C$2:$C$291,A6,'Test Cases'!$O$2:$O$291,"Fail") -> 0 | L6: =COUNTIFS('Test Cases'!$C$2:$C$291,A6,'Test Cases'!$O$2:$O$291,"Not Run") -> 4 | M6: =IF(K6>0,"Fail",IF(J6=F6,"Pass",IF(L6=F6,"Not Run","In Progress"))) -> Not Run
A7: US-06 | B7: Session timeout & re-authentication | C7: M01 | D7: Medium | E7: 2 | F7: =COUNTIF('Test Cases'!$C$2:$C$291,A7) -> 4 | G7: TC-US06-01 | H7: TC-US06-04 | I7: E2E-05, E2E-14 | J7: =COUNTIFS('Test Cases'!$C$2:$C$291,A7,'Test Cases'!$O$2:$O$291,"Pass") -> 0 | K7: =COUNTIFS('Test Cases'!$C$2:$C$291,A7,'Test Cases'!$O$2:$O$291,"Fail") -> 0 | L7: =COUNTIFS('Test Cases'!$C$2:$C$291,A7,'Test Cases'!$O$2:$O$291,"Not Run") -> 4 | M7: =IF(K7>0,"Fail",IF(J7=F7,"Pass",IF(L7=F7,"Not Run","In Progress"))) -> Not Run
A8: US-07 | B8: Guest checkout | C8: M01 | D8: High | E8: 3 | F8: =COUNTIF('Test Cases'!$C$2:$C$291,A8) -> 6 | G8: TC-US07-01 | H8: TC-US07-06 | I8: E2E-02 | J8: =COUNTIFS('Test Cases'!$C$2:$C$291,A8,'Test Cases'!$O$2:$O$291,"Pass") -> 0 | K8: =COUNTIFS('Test Cases'!$C$2:$C$291,A8,'Test Cases'!$O$2:$O$291,"Fail") -> 0 | L8: =COUNTIFS('Test Cases'!$C$2:$C$291,A8,'Test Cases'!$O$2:$O$291,"Not Run") -> 6 | M8: =IF(K8>0,"Fail",IF(J8=F8,"Pass",IF(L8=F8,"Not Run","In Progress"))) -> Not Run
A9: US-08 | B9: Homepage sections | C9: M02 | D9: Medium | E9: 3 | F9: =COUNTIF('Test Cases'!$C$2:$C$291,A9) -> 6 | G9: TC-US08-01 | H9: TC-US08-06 | I9: E2E-22 | J9: =COUNTIFS('Test Cases'!$C$2:$C$291,A9,'Test Cases'!$O$2:$O$291,"Pass") -> 0 | K9: =COUNTIFS('Test Cases'!$C$2:$C$291,A9,'Test Cases'!$O$2:$O$291,"Fail") -> 0 | L9: =COUNTIFS('Test Cases'!$C$2:$C$291,A9,'Test Cases'!$O$2:$O$291,"Not Run") -> 6 | M9: =IF(K9>0,"Fail",IF(J9=F9,"Pass",IF(L9=F9,"Not Run","In Progress"))) -> Not Run
A10: US-09 | B10: Main navigation menu | C10: M02 | D10: Medium | E10: 3 | F10: =COUNTIF('Test Cases'!$C$2:$C$291,A10) -> 6 | G10: TC-US09-01 | H10: TC-US09-06 | I10: E2E-18, E2E-19, E2E-22 | J10: =COUNTIFS('Test Cases'!$C$2:$C$291,A10,'Test Cases'!$O$2:$O$291,"Pass") -> 0 | K10: =COUNTIFS('Test Cases'!$C$2:$C$291,A10,'Test Cases'!$O$2:$O$291,"Fail") -> 0 | L10: =COUNTIFS('Test Cases'!$C$2:$C$291,A10,'Test Cases'!$O$2:$O$291,"Not Run") -> 6 | M10: =IF(K10>0,"Fail",IF(J10=F10,"Pass",IF(L10=F10,"Not Run","In Progress"))) -> Not Run
A11: US-10 | B11: Breadcrumb navigation | C11: M02 | D11: Low | E11: 2 | F11: =COUNTIF('Test Cases'!$C$2:$C$291,A11) -> 4 | G11: TC-US10-01 | H11: TC-US10-04 | I11: E2E-22 | J11: =COUNTIFS('Test Cases'!$C$2:$C$291,A11,'Test Cases'!$O$2:$O$291,"Pass") -> 0 | K11: =COUNTIFS('Test Cases'!$C$2:$C$291,A11,'Test Cases'!$O$2:$O$291,"Fail") -> 0 | L11: =COUNTIFS('Test Cases'!$C$2:$C$291,A11,'Test Cases'!$O$2:$O$291,"Not Run") -> 4 | M11: =IF(K11>0,"Fail",IF(J11=F11,"Pass",IF(L11=F11,"Not Run","In Progress"))) -> Not Run
A12: US-11 | B12: Footer policy links | C12: M02 | D12: Low | E12: 2 | F12: =COUNTIF('Test Cases'!$C$2:$C$291,A12) -> 4 | G12: TC-US11-01 | H12: TC-US11-04 | I12: E2E-22 | J12: =COUNTIFS('Test Cases'!$C$2:$C$291,A12,'Test Cases'!$O$2:$O$291,"Pass") -> 0 | K12: =COUNTIFS('Test Cases'!$C$2:$C$291,A12,'Test Cases'!$O$2:$O$291,"Fail") -> 0 | L12: =COUNTIFS('Test Cases'!$C$2:$C$291,A12,'Test Cases'!$O$2:$O$291,"Not Run") -> 4 | M12: =IF(K12>0,"Fail",IF(J12=F12,"Pass",IF(L12=F12,"Not Run","In Progress"))) -> Not Run
A13: US-12 | B13: Keyword search | C13: M03 | D13: Critical | E13: 4 | F13: =COUNTIF('Test Cases'!$C$2:$C$291,A13) -> 8 | G13: TC-US12-01 | H13: TC-US12-08 | I13: E2E-01, E2E-04, E2E-20, E2E-21 | J13: =COUNTIFS('Test Cases'!$C$2:$C$291,A13,'Test Cases'!$O$2:$O$291,"Pass") -> 0 | K13: =COUNTIFS('Test Cases'!$C$2:$C$291,A13,'Test Cases'!$O$2:$O$291,"Fail") -> 0 | L13: =COUNTIFS('Test Cases'!$C$2:$C$291,A13,'Test Cases'!$O$2:$O$291,"Not Run") -> 8 | M13: =IF(K13>0,"Fail",IF(J13=F13,"Pass",IF(L13=F13,"Not Run","In Progress"))) -> Not Run
... A61: US-60 | B61: Error pages (404 / 500) | C61: M10 | D61: Low | E61: 2 | F61: =COUNTIF('Test Cases'!$C$2:$C$291,A61) -> 4 | G61: TC-US60-01 | H61: TC-US60-04 | I61: E2E-22 | J61: =COUNTIFS('Test Cases'!$C$2:$C$291,A61,'Test Cases'!$O$2:$O$291,"Pass") -> 0 | K61: =COUNTIFS('Test Cases'!$C$2:$C$291,A61,'Test Cases'!$O$2:$O$291,"Fail") -> 0 | L61: =COUNTIFS('Test Cases'!$C$2:$C$291,A61,'Test Cases'!$O$2:$O$291,"Not Run") -> 4 | M61: =IF(K61>0,"Fail",IF(J61=F61,"Pass",IF(L61=F61,"Not Run","In Progress"))) -> Not Run
